awskeyspaces/AmazonRootCA1.pem
awskeyspaces/__init__.py
awskeyspaces/auth.py
awskeyspaces/config.py
awskeyspaces/connection.py
awskeyspaces/profile.py
awskeyspaces/util.py
awskeyspaces-1.0.8.dist-info/LICENSE
awskeyspaces-1.0.8.dist-info/METADATA
awskeyspaces-1.0.8.dist-info/WHEEL
awskeyspaces-1.0.8.dist-info/top_level.txt
awskeyspaces-1.0.8.dist-info/RECORD
