Metadata-Version: 2.1
Name: awskeyspaces
Version: 1.0.8
Summary: A simple package to connect into AWS KEYSPACES (cassandra)
Home-page: https://bitbucket.com/labunix/keyspaces.git
Download-URL: https://bitbucket.com/labunix/awskeyspaces/get/master.tar.gz
Author: Julio Quierati
Author-email: Julio Quierati <quierati@labunix.dev>
Project-URL: Homepage, https://bitbucket.org/labunix/awskeyspaces
Classifier: Programming Language :: Python :: 3
Classifier: License :: OSI Approved :: MIT License
Classifier: Operating System :: OS Independent
Requires-Python: >=3.8
License-File: LICENSE
